tiny_dashboard/__init__.py
tiny_dashboard/dashboard_implementations.py
tiny_dashboard/feature_centric_dashboards.py
tiny_dashboard/html_utils.py
tiny_dashboard/utils.py
tiny_dashboard/visualization_utils.py
tiny_dashboard/templates/base.html
tiny_dashboard/templates/click_to_expand.html
tiny_dashboard/templates/end_of_collapsed.html
tiny_dashboard/templates/example_container.html
tiny_dashboard/templates/feature_section.html
tiny_dashboard/templates/listeners.js
tiny_dashboard/templates/styles.css
tiny_dashboard/templates/token.html
tiny_dashboard-0.5.4.dist-info/METADATA
tiny_dashboard-0.5.4.dist-info/WHEEL
tiny_dashboard-0.5.4.dist-info/top_level.txt
tiny_dashboard-0.5.4.dist-info/RECORD
