Metadata-Version: 2.2
Name: tiny-dashboard
Version: 0.5.4
Summary: A tool for visualizing and exploring feature activations in neural language models.
Author-email: Clément Dumas <butanium.contact@gmail.com>
Project-URL: Homepage, https://github.com/butanium/tiny-activation-dashboard
Classifier: Programming Language :: Python :: 3
Classifier: License :: OSI Approved :: MIT License
Classifier: Operating System :: OS Independent
Requires-Python: >=3.8
Requires-Dist: nnterp
Requires-Dist: ipywidgets
